optimal_splitk/__init__.py
optimal_splitk/doe.py
optimal_splitk/encode.py
optimal_splitk/init.py
optimal_splitk/optimizers.py
optimal_splitk/utils.py
optimal_splitk/validation.py
optimal_splitk/optim/__init__.py
optimal_splitk/optim/doptim.py
optimal_splitk/optim/ioptim.py
optimal_splitk-0.0.2.dist-info/LICENSE
optimal_splitk-0.0.2.dist-info/METADATA
optimal_splitk-0.0.2.dist-info/WHEEL
optimal_splitk-0.0.2.dist-info/top_level.txt
optimal_splitk-0.0.2.dist-info/RECORD
