Metadata-Version: 2.1
Name: optimal_splitk
Version: 0.0.2
Summary: DOE library for optimal split^k-plot designs with the coordinate exchange algorithm
Author: Mathias Born
Author-email: Mathias Born <mathias.born@kuleuven.be>
License: BSD 3-Clause License
Project-URL: homepage, https://github.com/mborn1/optimal_splitk
Project-URL: documentation, https://github.com/mborn1/optimal_splitk
Project-URL: repository, https://github.com/mborn1/optimal_splitk
Classifier: Environment :: Console
Classifier: Intended Audience :: Science/Research
Classifier: License :: OSI Approved :: BSD License
Classifier: Operating System :: OS Independent
Classifier: Programming Language :: Python
Classifier: Programming Language :: Python :: 3
Classifier: Topic :: Scientific/Engineering
Requires-Python: >=3.8
License-File: LICENSE
Requires-Dist: numba ==0.55.1
Requires-Dist: numpy ==1.21.5
Requires-Dist: tqdm ==4.64.0
Requires-Dist: scipy ==1.8.0
Provides-Extra: dev
Requires-Dist: sphinx ~=4.4 ; extra == 'dev'
Requires-Dist: docutils <0.18 ; extra == 'dev'
Requires-Dist: numpydoc ~=1.2 ; extra == 'dev'
Requires-Dist: pydata-sphinx-theme ~=0.7 ; extra == 'dev'
Requires-Dist: sphinx-copybutton ~=0.5 ; extra == 'dev'
Provides-Extra: examples
Requires-Dist: pandas ==1.5.0 ; extra == 'examples'
Requires-Dist: openpyxl ==3.0.10 ; extra == 'examples'
